delta/__init__.py
delta/compat.py
delta/compat_test.py
delta/main.py
delta/configs/atis2_nlu_joint_lstm_crf.yml
delta/configs/atis_nlu_joint_lstm_crf.yml
delta/configs/cnn_cls_mock.yml
delta/configs/cnn_daily_mail_s2s_lstm.yml
delta/configs/cnn_daily_mail_s2s_transformer.yml
delta/configs/conll_2003_seq_label_bert.yml
delta/configs/conll_2003_seq_label_elmo.yml
delta/configs/conll_2003_seq_label_lstm_crf.yml
delta/configs/han_cls_mock.yml
delta/configs/nlu_joint_mock.yml
delta/configs/rnn_match_mock.yml
delta/configs/seq_label_mock.yml
delta/configs/snli_match_rnn.yml
delta/configs/transformer_s2s_mock.yml
delta/configs/trec_text_cls_cnn.yml
delta/configs/yahoo_answer_text_cls_han.yml
delta/data/__init__.py
delta/data/datasets/__init__.py
delta/data/datasets/atis.py
delta/data/datasets/atis2.py
delta/data/datasets/atis2_test.py
delta/data/datasets/atis_test.py
delta/data/datasets/base_dataset.py
delta/data/datasets/build.py
delta/data/datasets/conll_2003.py
delta/data/datasets/conll_2003_test.py
delta/data/datasets/mock_text_cls_data.py
delta/data/datasets/mock_text_cls_test.py
delta/data/datasets/mock_text_match_data.py
delta/data/datasets/mock_text_match_test.py
delta/data/datasets/mock_text_nlu_joint_data.py
delta/data/datasets/mock_text_nlu_joint_test.py
delta/data/datasets/mock_text_seq2seq_data.py
delta/data/datasets/mock_text_seq2seq_test.py
delta/data/datasets/mock_text_seq_label_data.py
delta/data/datasets/mock_text_seq_label_test.py
delta/data/datasets/snli.py
delta/data/datasets/snli_test.py
delta/data/datasets/trec.py
delta/data/datasets/trec_test.py
delta/data/datasets/utils.py
delta/data/datasets/yahoo_answer.py
delta/data/datasets/yahoo_answer_test.py
delta/data/feat/__init__.py
delta/data/feat/speech_feature.py
delta/data/feat/speech_feature_test.py
delta/data/feat/speech_ops.py
delta/data/feat/speech_ops_test.py
delta/data/feat/tf_speech_feature.py
delta/data/feat/tf_speech_feature_test.py
delta/data/feat/python_speech_features/__init__.py
delta_nlp-0.3.2.dist-info/LICENSE
delta_nlp-0.3.2.dist-info/METADATA
delta_nlp-0.3.2.dist-info/WHEEL
delta_nlp-0.3.2.dist-info/entry_points.txt
delta_nlp-0.3.2.dist-info/top_level.txt
delta_nlp-0.3.2.dist-info/RECORD
